{
  "project_info": {
    "project_number": "788347894314",
    "firebase_url": "https://dziczyzna-b91b0.firebaseio.com",
    "project_id": "dziczyzna-b91b0",
    "storage_bucket": "dziczyzna-b91b0.appspot.com"
  },
  "client": [
    {
      "client_info": {
        "mobilesdk_app_id": "1:788347894314:android:40873057b67e50d4f8e153",
        "android_client_info": {
          "package_name": "pl.dziczyzna"
        }
      },
      "oauth_client": [
        {
          "client_id": "788347894314-fud95rpj9ujk48qc20gn3inbu54efrkn.apps.googleusercontent.com",
          "client_type": 3
        }
      ],
      "api_key": [
        {
          "current_key": "AIzaSyAv09SkaPI4AQ84GcOie9ownIQovJYqeco"
        }
      ],
      "services": {
        "appinvite_service": {
          "other_platform_oauth_client": [
            {
              "client_id": "788347894314-fud95rpj9ujk48qc20gn3inbu54efrkn.apps.googleusercontent.com",
              "client_type": 3
            }
          ]
        }
      }
    }
  ],
  "configuration_version": "1"
}